addoneaddmat/__init__.py
addoneaddmat/addone.py
addoneaddmat/extras/__init__.py
addoneaddmat/extras/addvec.py
addoneaddmat-0.0.5.dist-info/METADATA
addoneaddmat-0.0.5.dist-info/WHEEL
addoneaddmat-0.0.5.dist-info/top_level.txt
addoneaddmat-0.0.5.dist-info/RECORD
